{
  "items": {
    "%[sd]": "%(\\d\\$)?[sd]",
    "!": "！",
    ",": "，",
    ":": "：",
    ";": "；",
    "[^.]\\.(?!\\.|ics)": "。",
    "<": "<",
    ">": ">",
    "\\((?!s).*?\\)": "（.*?）|\\(\\)",
    "\"\\.+\"": "“\\.+”",
    "'\\.+'": "‘\\.+’",
    "\\*\\*[\\S\\s]+?\\*\\*": "\\*\\*[\\S\\s]+?\\*\\*",
    "\n": "\n",
    "\\.{3}": "…",
    "\\?": "？",
    "no .+ found": "^没有\\.+找到",
    "«": "«",
    "»": "»"
  },
  "exceptions": {
    "\\((?!s).*?\\)": [
      "%s DIFF LINK(S)",
      "%s ERROR(S)"
    ],
    "[^.]\\.(?!\\.|ics)": [
      "ldap.example.com",
      "ldaps://ldaps.example.com/",
      "ou=People, dc=example, dc=com",
      "Replaced by 'phid.query'."
    ],
    ":": [
      "ldaps://ldaps.example.com/"
    ],
    ",": [
      "ou=People, dc=example, dc=com",
      "user=%s, should_verify=%s",
      "user=%s, verified=%s, primary=%s, should_verify=%s"
    ]
  }
}

